{"stepIndex": 35, "stepCount": 40, "step": {"title": "Step 36", "sourceEventIndex": 169, "event": {"type": "analysis", "state": "NOT_FINISHED", "score": 0, "level": 1, "board": [[5, 5, 5, 5, 5, 5, 5, 5, 5, 5, 5, 5, 5, 5, 5, 5, 5, 5, 5, 5, 5, 5, 5, 5, 5, 5, 5, 5, 5, 5, 5, 5, 5, 5, 5, 5, 5, 5, 5, 5, 5, 5, 5, 5, 5, 5, 5, 5, 5, 5, 5, 5, 5, 5, 5, 5, 5, 5, 5, 5, 5, 5, 0, 0], [5, 5, 5, 5, 5, 5, 5, 5, 5, 5, 5, 5, 5, 5, 5, 5, 5, 5, 5, 5, 5, 5, 5, 5, 5, 5, 5, 5, 5, 5, 5, 5, 5, 5, 5, 5, 5, 5, 5, 5, 5, 5, 5, 5, 5, 5, 5, 5, 5, 5, 5, 5, 5, 5, 5, 5, 5, 5, 5, 5, 5, 5, 0, 0], [5, 5, 5, 5, 5, 5, 5, 5, 5, 5, 5, 5, 5, 5, 5, 5, 5, 5, 5, 5, 5, 5, 5, 5, 5, 5, 5, 5, 5, 5, 5, 5, 5, 5, 5, 5, 5, 5, 5, 5, 5, 5, 5, 5, 5, 5, 5, 5, 5, 5, 5, 5, 5, 5, 5, 5, 5, 5, 5, 5, 5, 5, 14, 14], [5, 5, 5, 5, 5, 5, 5, 5, 5, 5, 5, 5, 5, 5, 5, 5, 5, 5, 5, 5, 5, 5, 5, 5, 5, 5, 5, 5, 5, 5, 5, 5, 5, 5, 5, 5, 5, 5, 5, 5, 5, 5, 5, 5, 5, 5, 5, 5, 5, 5, 5, 5, 5, 5, 5, 5, 5, 5, 5, 5, 5, 5, 14, 14], [5, 5, 5, 5, 5, 5, 5, 5, 5, 5, 5, 5, 5, 5, 5, 5, 5, 5, 5, 5, 5, 5, 5, 5, 5, 5, 5, 5, 5, 5, 5, 5, 5, 5, 5, 5, 5, 5, 5, 5, 5, 5, 5, 5, 5, 5, 5, 5, 5, 5, 5, 5, 5, 5, 5, 5, 5, 5, 5, 5, 5, 5, 14, 14], [5, 5, 5, 5, 5, 5, 5, 5, 5, 5, 5, 5, 5, 5, 5, 5, 5, 5, 5, 5, 5, 5, 5, 5, 5, 5, 5, 5, 5, 5, 5, 5, 5, 5, 5, 5, 5, 5, 5, 5, 5, 5, 5, 5, 5, 5, 5, 5, 5, 5, 5, 5, 5, 5, 5, 5, 5, 5, 5, 5, 5, 5, 14, 14], [5, 5, 5, 5, 5, 5, 5, 5, 5, 5, 5, 5, 5, 5, 5, 5, 5, 5, 5, 5, 5, 5, 5, 5, 5, 5, 5, 5, 5, 5, 5, 5, 5, 5, 5, 5, 5, 5, 5, 5, 5, 5, 5, 5, 5, 5, 5, 5, 5, 5, 5, 5, 5, 5, 5, 5, 5, 5, 5, 5, 5, 5, 14, 14], [5, 5, 5, 5, 5, 5, 5, 5, 5, 5, 5, 5, 5, 5, 5, 5, 5, 5, 5, 5, 5, 5, 5, 5, 5, 5, 5, 5, 5, 5, 5, 5, 5, 5, 5, 5, 5, 5, 5, 5, 5, 5, 5, 5, 5, 5, 5, 5, 5, 5, 5, 5, 5, 5, 5, 5, 5, 5, 5, 5, 5, 5, 14, 14], [5, 5, 5, 5, 5, 5, 5, 5, 5, 5, 5, 5, 5, 5, 5, 5, 5, 5, 5, 5, 5, 5, 5, 5, 5, 5, 5, 5, 5, 5, 5, 5, 5, 5, 5, 5, 5, 5, 5, 5, 5, 5, 5, 5, 5, 5, 5, 5, 5, 5, 5, 5, 5, 5, 5, 5, 5, 5, 5, 5, 5, 5, 14, 14], [5, 5, 5, 5, 5, 5, 5, 5, 5, 5, 5, 5, 5, 5, 5, 5, 5, 5, 5, 5, 5, 5, 5, 5, 5, 5, 5, 5, 5, 5, 5, 5, 5, 5, 5, 5, 5, 5, 5, 5, 5, 5, 5, 5, 5, 5, 5, 5, 5, 5, 5, 5, 5, 5, 5, 5, 5, 5, 5, 5, 5, 5, 14, 14], [5, 5, 5, 5, 5, 5, 5, 5, 5, 5, 5, 5, 5, 5, 5, 5, 5, 5, 5, 5, 5, 5, 5, 5, 5, 5, 5, 5, 5, 5, 5, 5, 5, 5, 5, 5, 5, 5, 5, 5, 5, 5, 5, 5, 5, 5, 5, 5, 5, 5, 5, 5, 5, 5, 5, 5, 5, 5, 5, 5, 5, 5, 14, 14], [5, 5, 5, 5, 5, 5, 5, 5, 5, 5, 5, 5, 5, 5, 5, 5, 5, 5, 5, 5, 5, 5, 5, 5, 5, 5, 5, 5, 5, 5, 5, 5, 5, 5, 5, 5, 5, 5, 5, 5, 5, 5, 5, 5, 5, 5, 5, 5, 5, 5, 5, 5, 5, 5, 5, 5, 5, 5, 5, 5, 5, 5, 14, 14], [5, 5, 5, 5, 5, 5, 5, 5, 5, 5, 5, 5, 5, 5, 5, 5, 5, 5, 5, 5, 5, 5, 5, 5, 5, 5, 5, 5, 5, 5, 5, 5, 5, 5, 5, 5, 5, 5, 5, 5, 5, 5, 5, 5, 5, 5, 5, 5, 5, 5, 5, 5, 5, 5, 5, 5, 5, 5, 5, 5, 5, 5, 14, 14], [5, 5, 5, 5, 5, 5, 5, 5, 5, 5, 5, 5, 5, 5, 5, 5, 5, 5, 5, 5, 5, 5, 5, 5, 5, 5, 5, 5, 5, 5, 5, 5, 5, 5, 5, 5, 5, 5, 5, 5, 5, 5, 5, 5, 5, 5, 5, 5, 5, 5, 5, 5, 5, 5, 5, 5, 5, 5, 5, 5, 5, 5, 14, 14], [5, 5, 5, 5, 5, 5, 5, 5, 5, 5, 5, 5, 5, 5, 5, 5, 5, 5, 5, 5, 5, 5, 5, 5, 5, 5, 5, 5, 5, 5, 5, 5, 5, 5, 5, 5, 5, 5, 5, 5, 5, 5, 5, 5, 5, 5, 5, 5, 5, 5, 5, 5, 5, 5, 5, 5, 5, 5, 5, 5, 5, 5, 14, 14], [5, 5, 5, 5, 5, 5, 5, 5, 5, 5, 5, 5, 5, 5, 5, 5, 5, 5, 5, 5, 5, 5, 5, 5, 5, 5, 5, 5, 5, 5, 5, 5, 5, 5, 5, 5, 5, 5, 5, 5, 5, 5, 5, 5, 5, 5, 5, 5, 5, 5, 5, 5, 5, 5, 5, 5, 5, 5, 5, 5, 5, 5, 14, 14], [5, 5, 5, 5, 5, 5, 5, 5, 5, 5, 5, 5, 5, 5, 5, 5, 5, 5, 5, 5, 5, 5, 5, 5, 5, 5, 5, 5, 5, 5, 5, 5, 5, 5, 5, 5, 5, 5, 5, 5, 5, 5, 5, 5, 5, 5, 5, 5, 5, 5, 5, 5, 5, 5, 5, 5, 5, 5, 5, 5, 5, 5, 14, 14], [5, 5, 5, 5, 5, 5, 5, 5, 5, 5, 5, 5, 9, 9, 9, 9, 9, 5, 5, 5, 5, 5, 5, 5, 5, 5, 5, 5, 5, 5, 5, 5, 5, 5, 5, 5, 5, 5, 5, 5, 5, 5, 5, 5, 5, 5, 5, 5, 5, 5, 5, 5, 5, 5, 5, 5, 5, 5, 5, 5, 5, 5, 14, 14], [5, 5, 5, 5, 5, 5, 5, 5, 5, 5, 5, 5, 9, 10, 10, 10, 10, 5, 5, 5, 5, 5, 5, 5, 5, 5, 5, 5, 5, 5, 5, 5, 5, 5, 5, 5, 5, 5, 5, 5, 5, 5, 5, 5, 5, 5, 5, 5, 5, 5, 5, 5, 5, 5, 5, 5, 5, 5, 5, 5, 5, 5, 14, 14], [5, 5, 5, 5, 5, 5, 5, 5, 5, 5, 5, 5, 9, 10, 10, 10, 10, 2, 2, 2, 2, 2, 2, 2, 2, 2, 2, 2, 2, 2, 2, 2, 2, 2, 2, 2, 2, 2, 2, 10, 10, 9, 9, 5, 5, 5, 5, 5, 5, 5, 5, 5, 5, 5, 5, 5, 5, 5, 5, 5, 5, 5, 14, 14], [5, 5, 5, 5, 5, 5, 5, 5, 5, 5, 5, 5, 9, 10, 10, 10, 10, 2, 2, 2, 2, 2, 2, 2, 2, 2, 2, 2, 2, 2, 2, 2, 2, 2, 2, 2, 2, 2, 2, 10, 10, 9, 9, 5, 5, 5, 5, 5, 5, 5, 5, 5, 5, 5, 5, 5, 5, 5, 5, 5, 5, 5, 14, 14], [5, 5, 5, 5, 5, 5, 5, 5, 5, 5, 5, 5, 9, 10, 10, 10, 10, 5, 5, 5, 5, 5, 5, 2, 2, 2, 2, 2, 2, 2, 2, 2, 2, 2, 2, 2, 2, 2, 2, 10, 10, 9, 9, 5, 5, 5, 5, 5, 5, 5, 5, 5, 5, 5, 5, 5, 5, 5, 5, 5, 5, 5, 14, 14], [5, 5, 5, 5, 5, 5, 5, 5, 5, 5, 5, 5, 9, 9, 9, 9, 9, 5, 5, 5, 5, 5, 5, 2, 2, 2, 2, 2, 2, 2, 2, 2, 2, 2, 2, 2, 2, 2, 2, 10, 10, 9, 9, 5, 5, 5, 5, 5, 5, 5, 5, 5, 5, 5, 5, 5, 5, 5, 5, 5, 5, 5, 14, 14], [5, 5, 5, 5, 5, 5, 5, 5, 5, 5, 5, 5, 5, 5, 5, 5, 5, 5, 5, 5, 5, 5, 5, 5, 5, 5, 5, 5, 5, 5, 5, 5, 5, 5, 5, 5, 5, 5, 5, 5, 5, 5, 5, 5, 5, 5, 5, 5, 5, 5, 5, 5, 5, 5, 5, 5, 5, 5, 5, 5, 5, 5, 14, 14], [5, 5, 5, 5, 5, 5, 5, 5, 5, 5, 5, 5, 5, 5, 5, 5, 5, 5, 5, 5, 5, 5, 5, 5, 5, 5, 5, 5, 5, 5, 5, 5, 5, 5, 5, 5, 5, 5, 5, 5, 5, 5, 5, 5, 5, 5, 5, 5, 5, 5, 5, 5, 5, 5, 5, 5, 5, 5, 5, 5, 5, 5, 14, 14], [5, 5, 5, 5, 5, 5, 5, 5, 5, 5, 5, 5, 5, 5, 5, 5, 5, 5, 5, 5, 5, 5, 5, 5, 5, 5, 5, 5, 5, 5, 5, 5, 5, 5, 5, 5, 5, 5, 5, 5, 5, 5, 5, 5, 5, 5, 5, 5, 5, 5, 5, 5, 5, 5, 5, 5, 5, 5, 5, 5, 5, 5, 14, 14], [5, 5, 5, 5, 5, 5, 5, 5, 5, 5, 5, 5, 5, 5, 5, 5, 5, 5, 5, 5, 5, 5, 5, 5, 5, 5, 5, 5, 5, 5, 5, 5, 5, 5, 5, 5, 5, 5, 5, 5, 5, 5, 5, 5, 5, 5, 5, 5, 5, 5, 5, 5, 5, 5, 5, 5, 5, 5, 5, 5, 5, 5, 14, 14], [5, 5, 5, 5, 5, 5, 5, 5, 5, 5, 5, 5, 5, 5, 5, 5, 5, 5, 5, 5, 5, 5, 5, 5, 5, 5, 5, 5, 5, 5, 5, 5, 5, 5, 5, 5, 5, 5, 5, 5, 5, 5, 5, 5, 5, 5, 5, 5, 5, 5, 5, 5, 5, 5, 5, 5, 5, 5, 5, 5, 5, 5, 14, 14], [5, 5, 5, 5, 5, 5, 5, 5, 5, 5, 5, 5, 5, 5, 5, 5, 5, 5, 5, 5, 5, 5, 5, 5, 5, 5, 5, 5, 5, 5, 5, 5, 5, 5, 5, 5, 5, 5, 5, 5, 5, 5, 5, 5, 5, 5, 5, 5, 5, 5, 5, 5, 5, 5, 5, 5, 5, 5, 5, 5, 5, 5, 14, 14], [5, 5, 5, 5, 5, 5, 5, 5, 5, 5, 5, 5, 5, 5, 5, 5, 5, 5, 5, 5, 5, 5, 5, 5, 5, 5, 5, 5, 5, 5, 5, 5, 5, 5, 5, 5, 5, 5, 5, 5, 5, 5, 5, 5, 5, 5, 5, 5, 5, 5, 5, 5, 5, 5, 5, 5, 5, 5, 5, 5, 5, 5, 14, 14], [5, 5, 5, 5, 5, 5, 5, 5, 5, 5, 5, 5, 5, 5, 5, 5, 5, 5, 5, 5, 5, 5, 5, 5, 5, 5, 5, 5, 5, 5, 5, 5, 5, 5, 5, 5, 5, 5, 5, 5, 5, 5, 5, 5, 5, 5, 5, 5, 5, 5, 5, 5, 5, 5, 5, 5, 5, 5, 5, 5, 5, 5, 14, 14], [5, 5, 5, 5, 5, 5, 5, 5, 5, 5, 5, 5, 5, 5, 5, 5, 5, 5, 5, 5, 5, 5, 5, 5, 5, 5, 5, 5, 5, 5, 5, 5, 5, 5, 5, 5, 5, 5, 5, 5, 5, 5, 5, 5, 5, 5, 5, 5, 5, 5, 5, 5, 5, 5, 5, 5, 5, 5, 5, 5, 5, 5, 14, 14], [5, 5, 5, 5, 5, 5, 5, 5, 5, 5, 5, 5, 5, 5, 5, 5, 5, 5, 5, 5, 5, 5, 5, 5, 5, 5, 5, 5, 5, 5, 5, 5, 5, 5, 5, 5, 5, 5, 5, 5, 5, 5, 5, 5, 5, 5, 5, 5, 5, 5, 5, 5, 5, 5, 5, 5, 5, 5, 5, 5, 5, 5, 14, 14], [5, 5, 5, 5, 5, 5, 5, 5, 5, 5, 5, 5, 5, 5, 5, 5, 5, 5, 5, 5, 5, 5, 5, 5, 5, 5, 5, 5, 5, 5, 5, 5, 5, 5, 5, 5, 5, 5, 5, 5, 5, 5, 5, 5, 5, 5, 5, 5, 5, 5, 5, 5, 5, 5, 5, 5, 5, 5, 5, 5, 5, 5, 14, 14], [5, 5, 5, 5, 5, 5, 5, 5, 5, 5, 5, 5, 5, 5, 5, 5, 5, 5, 5, 5, 5, 5, 5, 5, 5, 5, 5, 5, 5, 5, 5, 5, 5, 5, 5, 5, 5, 5, 5, 5, 5, 5, 5, 5, 5, 5, 5, 5, 5, 5, 5, 5, 5, 5, 5, 5, 5, 5, 5, 5, 5, 5, 14, 14], [5, 5, 5, 5, 5, 5, 5, 5, 5, 5, 5, 5, 5, 5, 5, 5, 5, 5, 5, 5, 5, 5, 5, 5, 5, 5, 5, 5, 5, 5, 5, 5, 5, 5, 5, 5, 5, 5, 5, 5, 5, 5, 5, 5, 5, 5, 5, 5, 5, 5, 5, 5, 5, 5, 5, 5, 5, 5, 5, 5, 5, 5, 14, 14], [5, 5, 5, 5, 5, 5, 5, 5, 5, 5, 5, 5, 5, 5, 5, 5, 5, 5, 5, 5, 5, 5, 5, 5, 5, 5, 5, 5, 5, 5, 5, 5, 5, 5, 5, 5, 5, 5, 5, 5, 5, 5, 5, 5, 5, 5, 5, 5, 5, 5, 5, 5, 5, 5, 5, 5, 5, 5, 5, 5, 5, 5, 14, 14], [5, 5, 5, 5, 5, 5, 5, 5, 5, 5, 5, 5, 5, 5, 5, 5, 5, 5, 5, 5, 5, 5, 5, 5, 5, 5, 5, 5, 5, 5, 5, 5, 5, 5, 5, 5, 5, 5, 5, 5, 5, 5, 5, 5, 5, 5, 5, 5, 5, 5, 5, 5, 5, 5, 5, 5, 5, 5, 5, 5, 5, 5, 14, 14], [5, 5, 5, 5, 5, 5, 5, 5, 5, 5, 5, 5, 5, 5, 5, 5, 5, 5, 5, 5, 5, 5, 5, 5, 5, 5, 5, 5, 5, 5, 5, 5, 5, 5, 5, 5, 5, 5, 5, 5, 5, 5, 5, 5, 5, 5, 5, 5, 5, 5, 5, 5, 5, 5, 5, 5, 5, 5, 5, 5, 5, 5, 14, 14], [5, 5, 5, 5, 5, 5, 5, 5, 5, 5, 5, 5, 5, 5, 5, 5, 5, 5, 5, 5, 5, 5, 5, 5, 5, 5, 5, 5, 5, 5, 5, 5, 5, 5, 5, 5, 5, 5, 5, 5, 5, 5, 5, 5, 5, 5, 5, 5, 5, 5, 5, 5, 5, 5, 5, 5, 5, 5, 5, 5, 5, 5, 14, 14], [5, 5, 5, 5, 5, 5, 5, 5, 5, 5, 5, 5, 5, 5, 5, 5, 5, 5, 5, 5, 5, 5, 5, 5, 5, 5, 5, 5, 5, 5, 5, 5, 5, 5, 5, 5, 5, 5, 5, 5, 5, 5, 5, 5, 5, 5, 5, 5, 5, 5, 5, 5, 5, 5, 5, 5, 5, 5, 5, 5, 5, 5, 14, 14], [5, 5, 5, 5, 5, 5, 5, 5, 5, 5, 5, 5, 5, 5, 5, 5, 5, 5, 5, 5, 5, 5, 5, 5, 5, 5, 5, 5, 5, 5, 5, 5, 5, 5, 5, 5, 5, 5, 5, 5, 5, 5, 5, 5, 5, 5, 5, 5, 5, 5, 5, 5, 5, 5, 5, 5, 5, 5, 5, 5, 5, 5, 14, 14], [5, 5, 5, 5, 5, 5, 5, 5, 5, 5, 5, 5, 5, 5, 5, 5, 5, 5, 5, 5, 5, 5, 5, 5, 5, 5, 5, 5, 5, 5, 5, 5, 5, 5, 5, 5, 5, 5, 5, 5, 5, 5, 5, 5, 5, 5, 5, 5, 5, 5, 5, 5, 5, 5, 5, 5, 5, 5, 5, 5, 5, 5, 14, 14], [5, 5, 5, 5, 5, 5, 5, 5, 5, 5, 5, 5, 5, 5, 5, 5, 5, 5, 5, 5, 5, 5, 5, 5, 5, 5, 5, 5, 5, 5, 5, 5, 5, 5, 5, 5, 5, 5, 5, 5, 5, 5, 5, 5, 5, 5, 5, 5, 5, 5, 5, 5, 5, 5, 5, 5, 5, 5, 5, 5, 5, 5, 14, 14], [5, 5, 5, 5, 5, 5, 5, 5, 5, 5, 5, 5, 5, 5, 5, 5, 5, 5, 5, 5, 5, 5, 5, 5, 5, 5, 5, 5, 5, 5, 5, 5, 5, 5, 5, 5, 5, 5, 5, 5, 5, 5, 5, 5, 5, 5, 5, 5, 5, 5, 5, 5, 5, 5, 5, 5, 5, 5, 5, 5, 5, 5, 14, 14], [5, 5, 5, 5, 5, 5, 5, 5, 5, 5, 5, 5, 5, 5, 5, 5, 5, 5, 5, 5, 5, 5, 5, 5, 5, 5, 5, 5, 5, 5, 5, 5, 5, 5, 5, 5, 5, 5, 5, 5, 5, 5, 5, 5, 5, 5, 5, 5, 5, 5, 5, 5, 5, 5, 5, 5, 5, 5, 5, 5, 5, 5, 14, 14], [5, 5, 5, 5, 5, 5, 5, 5, 5, 5, 5, 5, 5, 5, 5, 5, 5, 5, 5, 5, 5, 5, 5, 5, 5, 5, 5, 5, 5, 5, 5, 5, 5, 5, 5, 5, 5, 5, 5, 5, 5, 5, 5, 5, 5, 5, 5, 5, 5, 5, 5, 5, 5, 5, 5, 5, 5, 5, 5, 5, 5, 5, 14, 14], [5, 5, 5, 5, 5, 5, 5, 5, 5, 5, 5, 5, 5, 5, 5, 5, 5, 5, 5, 5, 5, 5, 3, 3, 3, 3, 3, 3, 3, 3, 3, 3, 3, 3, 3, 3, 3, 3, 3, 5, 5, 5, 5, 5, 5, 5, 5, 5, 5, 5, 5, 5, 5, 5, 5, 5, 5, 5, 5, 5, 5, 5, 14, 14], [5, 5, 5, 5, 5, 5, 5, 5, 5, 5, 5, 5, 5, 5, 5, 5, 5, 5, 5, 5, 5, 5, 3, 3, 3, 3, 3, 3, 3, 3, 3, 3, 3, 3, 3, 3, 3, 3, 3, 5, 5, 5, 5, 5, 5, 5, 5, 5, 5, 5, 5, 5, 5, 5, 5, 5, 5, 5, 5, 5, 5, 5, 14, 14], [5, 5, 5, 5, 5, 5, 5, 5, 5, 5, 5, 5, 5, 5, 5, 5, 5, 5, 5, 5, 5, 5, 3, 3, 2, 2, 2, 3, 3, 14, 14, 14, 3, 3, 2, 2, 2, 3, 3, 5, 5, 5, 5, 5, 5, 5, 5, 5, 5, 5, 5, 5, 5, 5, 5, 5, 5, 5, 5, 5, 5, 5, 14, 14], [5, 5, 5, 5, 5, 5, 5, 5, 5, 5, 5, 3, 3, 3, 3, 3, 3, 3, 3, 3, 3, 5, 3, 3, 2, 2, 2, 3, 3, 14, 14, 14, 3, 3, 2, 2, 2, 3, 3, 5, 5, 5, 5, 5, 5, 5, 5, 5, 5, 5, 5, 5, 5, 5, 5, 5, 5, 5, 5, 5, 5, 5, 14, 14], [5, 5, 5, 5, 5, 5, 5, 5, 5, 5, 5, 3, 2, 2, 2, 15, 15, 2, 2, 2, 3, 5, 3, 3, 2, 2, 2, 3, 3, 14, 14, 14, 3, 3, 2, 2, 2, 3, 3, 5, 5, 5, 5, 5, 5, 5, 5, 5, 5, 5, 5, 5, 5, 5, 5, 5, 5, 5, 5, 5, 5, 5, 14, 14], [5, 5, 5, 5, 5, 5, 5, 5, 5, 5, 5, 3, 2, 2, 2, 15, 15, 2, 2, 2, 3, 5, 3, 3, 3, 3, 3, 3, 3, 3, 3, 3, 3, 3, 3, 3, 3, 3, 3, 5, 5, 5, 5, 5, 5, 5, 5, 5, 5, 5, 5, 5, 5, 5, 5, 5, 5, 5, 5, 5, 5, 5, 14, 14], [5, 5, 5, 5, 5, 5, 5, 5, 5, 5, 5, 3, 2, 2, 2, 2, 2, 2, 2, 2, 3, 5, 3, 3, 3, 3, 3, 3, 3, 3, 3, 3, 3, 3, 3, 3, 3, 3, 3, 5, 5, 5, 5, 5, 5, 5, 5, 5, 5, 5, 5, 5, 5, 5, 5, 5, 5, 5, 5, 5, 5, 5, 14, 14], [5, 5, 5, 5, 5, 5, 5, 5, 5, 5, 5, 3, 15, 15, 2, 2, 2, 2, 15, 15, 3, 5, 3, 3, 0, 0, 0, 3, 3, 2, 2, 2, 3, 3, 0, 0, 0, 3, 3, 5, 5, 5, 5, 5, 5, 5, 5, 5, 5, 5, 5, 5, 5, 5, 5, 5, 5, 5, 5, 5, 5, 5, 14, 14], [5, 5, 5, 5, 5, 5, 5, 5, 5, 5, 5, 3, 15, 15, 2, 2, 2, 2, 15, 15, 3, 5, 3, 3, 0, 0, 0, 3, 3, 2, 2, 2, 3, 3, 0, 0, 0, 3, 3, 5, 5, 5, 5, 5, 5, 5, 5, 5, 5, 5, 5, 5, 5, 5, 5, 5, 5, 5, 5, 5, 5, 5, 14, 14], [5, 5, 5, 5, 5, 5, 5, 5, 5, 5, 5, 3, 2, 2, 2, 2, 2, 2, 2, 2, 3, 5, 3, 3, 0, 0, 0, 3, 3, 2, 2, 2, 3, 3, 0, 0, 0, 3, 3, 5, 5, 5, 5, 5, 5, 5, 5, 5, 5, 5, 5, 5, 5, 5, 5, 5, 5, 5, 5, 5, 5, 5, 14, 14], [5, 5, 5, 5, 5, 5, 5, 5, 5, 5, 5, 3, 2, 2, 2, 15, 15, 2, 2, 2, 3, 5, 3, 3, 3, 3, 3, 3, 3, 3, 3, 3, 3, 3, 3, 3, 3, 3, 3, 5, 5, 5, 5, 5, 5, 5, 5, 5, 5, 5, 5, 5, 5, 5, 5, 5, 5, 5, 5, 5, 5, 5, 14, 14], [5, 5, 5, 5, 5, 5, 5, 5, 5, 5, 5, 3, 2, 2, 2, 15, 15, 2, 2, 2, 3, 5, 3, 3, 3, 3, 3, 3, 3, 3, 3, 3, 3, 3, 3, 3, 3, 3, 3, 5, 5, 5, 5, 5, 5, 5, 5, 5, 5, 5, 5, 5, 5, 5, 5, 5, 5, 5, 5, 5, 5, 5, 14, 14], [5, 5, 5, 5, 5, 5, 5, 5, 5, 5, 5, 3, 3, 3, 3, 3, 3, 3, 3, 3, 3, 5, 3, 3, 2, 2, 2, 3, 3, 0, 0, 0, 3, 3, 2, 2, 2, 3, 3, 5, 5, 5, 5, 5, 5, 5, 5, 5, 5, 5, 5, 5, 5, 5, 5, 5, 5, 5, 5, 5, 5, 5, 14, 14], [5, 5, 5, 5, 5, 5, 5, 5, 5, 5, 5, 5, 5, 5, 5, 5, 5, 5, 5, 5, 5, 5, 3, 3, 2, 2, 2, 3, 3, 0, 0, 0, 3, 3, 2, 2, 2, 3, 3, 5, 5, 5, 5, 5, 5, 5, 5, 5, 5, 5, 5, 5, 5, 5, 5, 5, 5, 5, 5, 5, 5, 5, 14, 14], [5, 5, 5, 5, 5, 5, 5, 5, 5, 5, 5, 5, 5, 5, 5, 5, 5, 5, 5, 5, 5, 5, 3, 3, 2, 2, 2, 3, 3, 0, 0, 0, 3, 3, 2, 2, 2, 3, 3, 5, 5, 5, 5, 5, 5, 5, 5, 5, 5, 5, 5, 5, 5, 5, 5, 5, 5, 5, 5, 5, 5, 5, 14, 14], [5, 5, 5, 5, 5, 5, 5, 5, 5, 5, 5, 5, 5, 5, 5, 5, 5, 5, 5, 5, 5, 5, 3, 3, 3, 3, 3, 3, 3, 3, 3, 3, 3, 3, 3, 3, 3, 3, 3, 5, 5, 5, 5, 5, 5, 5, 5, 5, 5, 5, 5, 5, 5, 5, 5, 5, 5, 5, 5, 5, 5, 5, 14, 14], [5, 5, 5, 5, 5, 5, 5, 5, 5, 5, 5, 5, 5, 5, 5, 5, 5, 5, 5, 5, 5, 5, 3, 3, 3, 3, 3, 3, 3, 3, 3, 3, 3, 3, 3, 3, 3, 3, 3, 5, 5, 5, 5, 5, 5, 5, 5, 5, 5, 5, 5, 5, 5, 5, 5, 5, 5, 5, 5, 5, 5, 5, 14, 14]]}, "boardEvent": {"type": "action", "action_display": "MOUSE(row=51, col=15)", "action_name": "ACTION6", "state": "NOT_FINISHED", "reward": 0.0, "score": 0, "level": 1, "board": [[5, 5, 5, 5, 5, 5, 5, 5, 5, 5, 5, 5, 5, 5, 5, 5, 5, 5, 5, 5, 5, 5, 5, 5, 5, 5, 5, 5, 5, 5, 5, 5, 5, 5, 5, 5, 5, 5, 5, 5, 5, 5, 5, 5, 5, 5, 5, 5, 5, 5, 5, 5, 5, 5, 5, 5, 5, 5, 5, 5, 5, 5, 14, 14], [5, 5, 5, 5, 5, 5, 5, 5, 5, 5, 5, 5, 5, 5, 5, 5, 5, 5, 5, 5, 5, 5, 5, 5, 5, 5, 5, 5, 5, 5, 5, 5, 5, 5, 5, 5, 5, 5, 5, 5, 5, 5, 5, 5, 5, 5, 5, 5, 5, 5, 5, 5, 5, 5, 5, 5, 5, 5, 5, 5, 5, 5, 14, 14], [5, 5, 5, 5, 5, 5, 5, 5, 5, 5, 5, 5, 5, 5, 5, 5, 5, 5, 5, 5, 5, 5, 5, 5, 5, 5, 5, 5, 5, 5, 5, 5, 5, 5, 5, 5, 5, 5, 5, 5, 5, 5, 5, 5, 5, 5, 5, 5, 5, 5, 5, 5, 5, 5, 5, 5, 5, 5, 5, 5, 5, 5, 14, 14], [5, 5, 5, 5, 5, 5, 5, 5, 5, 5, 5, 5, 5, 5, 5, 5, 5, 5, 5, 5, 5, 5, 5, 5, 5, 5, 5, 5, 5, 5, 5, 5, 5, 5, 5, 5, 5, 5, 5, 5, 5, 5, 5, 5, 5, 5, 5, 5, 5, 5, 5, 5, 5, 5, 5, 5, 5, 5, 5, 5, 5, 5, 14, 14], [5, 5, 5, 5, 5, 5, 5, 5, 5, 5, 5, 5, 5, 5, 5, 5, 5, 5, 5, 5, 5, 5, 5, 5, 5, 5, 5, 5, 5, 5, 5, 5, 5, 5, 5, 5, 5, 5, 5, 5, 5, 5, 5, 5, 5, 5, 5, 5, 5, 5, 5, 5, 5, 5, 5, 5, 5, 5, 5, 5, 5, 5, 14, 14], [5, 5, 5, 5, 5, 5, 5, 5, 5, 5, 5, 5, 5, 5, 5, 5, 5, 5, 5, 5, 5, 5, 5, 5, 5, 5, 5, 5, 5, 5, 5, 5, 5, 5, 5, 5, 5, 5, 5, 5, 5, 5, 5, 5, 5, 5, 5, 5, 5, 5, 5, 5, 5, 5, 5, 5, 5, 5, 5, 5, 5, 5, 14, 14], [5, 5, 5, 5, 5, 5, 5, 5, 5, 5, 5, 5, 5, 5, 5, 5, 5, 5, 5, 5, 5, 5, 5, 5, 5, 5, 5, 5, 5, 5, 5, 5, 5, 5, 5, 5, 5, 5, 5, 5, 5, 5, 5, 5, 5, 5, 5, 5, 5, 5, 5, 5, 5, 5, 5, 5, 5, 5, 5, 5, 5, 5, 14, 14], [5, 5, 5, 5, 5, 5, 5, 5, 5, 5, 5, 5, 5, 5, 5, 5, 5, 5, 5, 5, 5, 5, 5, 5, 5, 5, 5, 5, 5, 5, 5, 5, 5, 5, 5, 5, 5, 5, 5, 5, 5, 5, 5, 5, 5, 5, 5, 5, 5, 5, 5, 5, 5, 5, 5, 5, 5, 5, 5, 5, 5, 5, 14, 14], [5, 5, 5, 5, 5, 5, 5, 5, 5, 5, 5, 5, 5, 5, 5, 5, 5, 5, 5, 5, 5, 5, 5, 5, 5, 5, 5, 5, 5, 5, 5, 5, 5, 5, 5, 5, 5, 5, 5, 5, 5, 5, 5, 5, 5, 5, 5, 5, 5, 5, 5, 5, 5, 5, 5, 5, 5, 5, 5, 5, 5, 5, 14, 14], [5, 5, 5, 5, 5, 5, 5, 5, 5, 5, 5, 5, 5, 5, 5, 5, 5, 5, 5, 5, 5, 5, 5, 5, 5, 5, 5, 5, 5, 5, 5, 5, 5, 5, 5, 5, 5, 5, 5, 5, 5, 5, 5, 5, 5, 5, 5, 5, 5, 5, 5, 5, 5, 5, 5, 5, 5, 5, 5, 5, 5, 5, 14, 14], [5, 5, 5, 5, 5, 5, 5, 5, 5, 5, 5, 5, 5, 5, 5, 5, 5, 5, 5, 5, 5, 5, 5, 5, 5, 5, 5, 5, 5, 5, 5, 5, 5, 5, 5, 5, 5, 5, 5, 5, 5, 5, 5, 5, 5, 5, 5, 5, 5, 5, 5, 5, 5, 5, 5, 5, 5, 5, 5, 5, 5, 5, 14, 14], [5, 5, 5, 5, 5, 5, 5, 5, 5, 5, 5, 5, 5, 5, 5, 5, 5, 5, 5, 5, 5, 5, 5, 5, 5, 5, 5, 5, 5, 5, 5, 5, 5, 5, 5, 5, 5, 5, 5, 5, 5, 5, 5, 5, 5, 5, 5, 5, 5, 5, 5, 5, 5, 5, 5, 5, 5, 5, 5, 5, 5, 5, 14, 14], [5, 5, 5, 5, 5, 5, 5, 5, 5, 5, 5, 5, 5, 5, 5, 5, 5, 5, 5, 5, 5, 5, 5, 5, 5, 5, 5, 5, 5, 5, 5, 5, 5, 5, 5, 5, 5, 5, 5, 5, 5, 5, 5, 5, 5, 5, 5, 5, 5, 5, 5, 5, 5, 5, 5, 5, 5, 5, 5, 5, 5, 5, 14, 14], [5, 5, 5, 5, 5, 5, 5, 5, 5, 5, 5, 5, 5, 5, 5, 5, 5, 5, 5, 5, 5, 5, 5, 5, 5, 5, 5, 5, 5, 5, 5, 5, 5, 5, 5, 5, 5, 5, 5, 5, 5, 5, 5, 5, 5, 5, 5, 5, 5, 5, 5, 5, 5, 5, 5, 5, 5, 5, 5, 5, 5, 5, 14, 14], [5, 5, 5, 5, 5, 5, 5, 5, 5, 5, 5, 5, 5, 5, 5, 5, 5, 5, 5, 5, 5, 5, 5, 5, 5, 5, 5, 5, 5, 5, 5, 5, 5, 5, 5, 5, 5, 5, 5, 5, 5, 5, 5, 5, 5, 5, 5, 5, 5, 5, 5, 5, 5, 5, 5, 5, 5, 5, 5, 5, 5, 5, 14, 14], [5, 5, 5, 5, 5, 5, 5, 5, 5, 5, 5, 5, 5, 5, 5, 5, 5, 5, 5, 5, 5, 5, 5, 5, 5, 5, 5, 5, 5, 5, 5, 5, 5, 5, 5, 5, 5, 5, 5, 5, 5, 5, 5, 5, 5, 5, 5, 5, 5, 5, 5, 5, 5, 5, 5, 5, 5, 5, 5, 5, 5, 5, 14, 14], [5, 5, 5, 5, 5, 5, 5, 5, 5, 5, 5, 5, 5, 5, 5, 5, 5, 5, 5, 5, 5, 5, 5, 5, 5, 5, 5, 5, 5, 5, 5, 5, 5, 5, 5, 5, 5, 5, 5, 5, 5, 5, 5, 5, 5, 5, 5, 5, 5, 5, 5, 5, 5, 5, 5, 5, 5, 5, 5, 5, 5, 5, 14, 14], [5, 5, 5, 5, 5, 5, 5, 5, 5, 5, 5, 5, 9, 9, 9, 9, 9, 5, 5, 5, 5, 5, 5, 5, 5, 5, 5, 5, 5, 5, 5, 5, 5, 5, 5, 5, 5, 5, 5, 5, 5, 5, 5, 5, 5, 5, 5, 5, 5, 5, 5, 5, 5, 5, 5, 5, 5, 5, 5, 5, 5, 5, 14, 14], [5, 5, 5, 5, 5, 5, 5, 5, 5, 5, 5, 5, 9, 10, 10, 10, 10, 5, 5, 5, 5, 5, 5, 5, 5, 5, 5, 5, 5, 5, 5, 5, 5, 5, 5, 5, 5, 5, 5, 5, 5, 5, 5, 5, 5, 5, 5, 5, 5, 5, 5, 5, 5, 5, 5, 5, 5, 5, 5, 5, 5, 5, 14, 14], [5, 5, 5, 5, 5, 5, 5, 5, 5, 5, 5, 5, 9, 10, 10, 10, 10, 2, 2, 2, 2, 2, 2, 2, 2, 2, 2, 2, 2, 2, 2, 2, 2, 2, 2, 2, 2, 2, 2, 10, 10, 9, 9, 5, 5, 5, 5, 5, 5, 5, 5, 5, 5, 5, 5, 5, 5, 5, 5, 5, 5, 5, 14, 14], [5, 5, 5, 5, 5, 5, 5, 5, 5, 5, 5, 5, 9, 10, 10, 10, 10, 2, 2, 2, 2, 2, 2, 2, 2, 2, 2, 2, 2, 2, 2, 2, 2, 2, 2, 2, 2, 2, 2, 10, 10, 9, 9, 5, 5, 5, 5, 5, 5, 5, 5, 5, 5, 5, 5, 5, 5, 5, 5, 5, 5, 5, 14, 14], [5, 5, 5, 5, 5, 5, 5, 5, 5, 5, 5, 5, 9, 10, 10, 10, 10, 5, 5, 5, 5, 5, 5, 2, 2, 2, 2, 2, 2, 2, 2, 2, 2, 2, 2, 2, 2, 2, 2, 10, 10, 9, 9, 5, 5, 5, 5, 5, 5, 5, 5, 5, 5, 5, 5, 5, 5, 5, 5, 5, 5, 5, 14, 14], [5, 5, 5, 5, 5, 5, 5, 5, 5, 5, 5, 5, 9, 9, 9, 9, 9, 5, 5, 5, 5, 5, 5, 2, 2, 2, 2, 2, 2, 2, 2, 2, 2, 2, 2, 2, 2, 2, 2, 10, 10, 9, 9, 5, 5, 5, 5, 5, 5, 5, 5, 5, 5, 5, 5, 5, 5, 5, 5, 5, 5, 5, 14, 14], [5, 5, 5, 5, 5, 5, 5, 5, 5, 5, 5, 5, 5, 5, 5, 5, 5, 5, 5, 5, 5, 5, 5, 5, 5, 5, 5, 5, 5, 5, 5, 5, 5, 5, 5, 5, 5, 5, 5, 5, 5, 5, 5, 5, 5, 5, 5, 5, 5, 5, 5, 5, 5, 5, 5, 5, 5, 5, 5, 5, 5, 5, 14, 14], [5, 5, 5, 5, 5, 5, 5, 5, 5, 5, 5, 5, 5, 5, 5, 5, 5, 5, 5, 5, 5, 5, 5, 5, 5, 5, 5, 5, 5, 5, 5, 5, 5, 5, 5, 5, 5, 5, 5, 5, 5, 5, 5, 5, 5, 5, 5, 5, 5, 5, 5, 5, 5, 5, 5, 5, 5, 5, 5, 5, 5, 5, 14, 14], [5, 5, 5, 5, 5, 5, 5, 5, 5, 5, 5, 5, 5, 5, 5, 5, 5, 5, 5, 5, 5, 5, 5, 5, 5, 5, 5, 5, 5, 5, 5, 5, 5, 5, 5, 5, 5, 5, 5, 5, 5, 5, 5, 5, 5, 5, 5, 5, 5, 5, 5, 5, 5, 5, 5, 5, 5, 5, 5, 5, 5, 5, 14, 14], [5, 5, 5, 5, 5, 5, 5, 5, 5, 5, 5, 5, 5, 5, 5, 5, 5, 5, 5, 5, 5, 5, 5, 5, 5, 5, 5, 5, 5, 5, 5, 5, 5, 5, 5, 5, 5, 5, 5, 5, 5, 5, 5, 5, 5, 5, 5, 5, 5, 5, 5, 5, 5, 5, 5, 5, 5, 5, 5, 5, 5, 5, 14, 14], [5, 5, 5, 5, 5, 5, 5, 5, 5, 5, 5, 5, 5, 5, 5, 5, 5, 5, 5, 5, 5, 5, 5, 5, 5, 5, 5, 5, 5, 5, 5, 5, 5, 5, 5, 5, 5, 5, 5, 5, 5, 5, 5, 5, 5, 5, 5, 5, 5, 5, 5, 5, 5, 5, 5, 5, 5, 5, 5, 5, 5, 5, 14, 14], [5, 5, 5, 5, 5, 5, 5, 5, 5, 5, 5, 5, 5, 5, 5, 5, 5, 5, 5, 5, 5, 5, 5, 5, 5, 5, 5, 5, 5, 5, 5, 5, 5, 5, 5, 5, 5, 5, 5, 5, 5, 5, 5, 5, 5, 5, 5, 5, 5, 5, 5, 5, 5, 5, 5, 5, 5, 5, 5, 5, 5, 5, 14, 14], [5, 5, 5, 5, 5, 5, 5, 5, 5, 5, 5, 5, 5, 5, 5, 5, 5, 5, 5, 5, 5, 5, 5, 5, 5, 5, 5, 5, 5, 5, 5, 5, 5, 5, 5, 5, 5, 5, 5, 5, 5, 5, 5, 5, 5, 5, 5, 5, 5, 5, 5, 5, 5, 5, 5, 5, 5, 5, 5, 5, 5, 5, 14, 14], [5, 5, 5, 5, 5, 5, 5, 5, 5, 5, 5, 5, 5, 5, 5, 5, 5, 5, 5, 5, 5, 5, 5, 5, 5, 5, 5, 5, 5, 5, 5, 5, 5, 5, 5, 5, 5, 5, 5, 5, 5, 5, 5, 5, 5, 5, 5, 5, 5, 5, 5, 5, 5, 5, 5, 5, 5, 5, 5, 5, 5, 5, 14, 14], [5, 5, 5, 5, 5, 5, 5, 5, 5, 5, 5, 5, 5, 5, 5, 5, 5, 5, 5, 5, 5, 5, 5, 5, 5, 5, 5, 5, 5, 5, 5, 5, 5, 5, 5, 5, 5, 5, 5, 5, 5, 5, 5, 5, 5, 5, 5, 5, 5, 5, 5, 5, 5, 5, 5, 5, 5, 5, 5, 5, 5, 5, 14, 14], [5, 5, 5, 5, 5, 5, 5, 5, 5, 5, 5, 5, 5, 5, 5, 5, 5, 5, 5, 5, 5, 5, 5, 5, 5, 5, 5, 5, 5, 5, 5, 5, 5, 5, 5, 5, 5, 5, 5, 5, 5, 5, 5, 5, 5, 5, 5, 5, 5, 5, 5, 5, 5, 5, 5, 5, 5, 5, 5, 5, 5, 5, 14, 14], [5, 5, 5, 5, 5, 5, 5, 5, 5, 5, 5, 5, 5, 5, 5, 5, 5, 5, 5, 5, 5, 5, 5, 5, 5, 5, 5, 5, 5, 5, 5, 5, 5, 5, 5, 5, 5, 5, 5, 5, 5, 5, 5, 5, 5, 5, 5, 5, 5, 5, 5, 5, 5, 5, 5, 5, 5, 5, 5, 5, 5, 5, 14, 14], [5, 5, 5, 5, 5, 5, 5, 5, 5, 5, 5, 5, 5, 5, 5, 5, 5, 5, 5, 5, 5, 5, 5, 5, 5, 5, 5, 5, 5, 5, 5, 5, 5, 5, 5, 5, 5, 5, 5, 5, 5, 5, 5, 5, 5, 5, 5, 5, 5, 5, 5, 5, 5, 5, 5, 5, 5, 5, 5, 5, 5, 5, 14, 14], [5, 5, 5, 5, 5, 5, 5, 5, 5, 5, 5, 5, 5, 5, 5, 5, 5, 5, 5, 5, 5, 5, 5, 5, 5, 5, 5, 5, 5, 5, 5, 5, 5, 5, 5, 5, 5, 5, 5, 5, 5, 5, 5, 5, 5, 5, 5, 5, 5, 5, 5, 5, 5, 5, 5, 5, 5, 5, 5, 5, 5, 5, 14, 14], [5, 5, 5, 5, 5, 5, 5, 5, 5, 5, 5, 5, 5, 5, 5, 5, 5, 5, 5, 5, 5, 5, 5, 5, 5, 5, 5, 5, 5, 5, 5, 5, 5, 5, 5, 5, 5, 5, 5, 5, 5, 5, 5, 5, 5, 5, 5, 5, 5, 5, 5, 5, 5, 5, 5, 5, 5, 5, 5, 5, 5, 5, 14, 14], [5, 5, 5, 5, 5, 5, 5, 5, 5, 5, 5, 5, 5, 5, 5, 5, 5, 5, 5, 5, 5, 5, 5, 5, 5, 5, 5, 5, 5, 5, 5, 5, 5, 5, 5, 5, 5, 5, 5, 5, 5, 5, 5, 5, 5, 5, 5, 5, 5, 5, 5, 5, 5, 5, 5, 5, 5, 5, 5, 5, 5, 5, 14, 14], [5, 5, 5, 5, 5, 5, 5, 5, 5, 5, 5, 5, 5, 5, 5, 5, 5, 5, 5, 5, 5, 5, 5, 5, 5, 5, 5, 5, 5, 5, 5, 5, 5, 5, 5, 5, 5, 5, 5, 5, 5, 5, 5, 5, 5, 5, 5, 5, 5, 5, 5, 5, 5, 5, 5, 5, 5, 5, 5, 5, 5, 5, 14, 14], [5, 5, 5, 5, 5, 5, 5, 5, 5, 5, 5, 5, 5, 5, 5, 5, 5, 5, 5, 5, 5, 5, 5, 5, 5, 5, 5, 5, 5, 5, 5, 5, 5, 5, 5, 5, 5, 5, 5, 5, 5, 5, 5, 5, 5, 5, 5, 5, 5, 5, 5, 5, 5, 5, 5, 5, 5, 5, 5, 5, 5, 5, 14, 14], [5, 5, 5, 5, 5, 5, 5, 5, 5, 5, 5, 5, 5, 5, 5, 5, 5, 5, 5, 5, 5, 5, 5, 5, 5, 5, 5, 5, 5, 5, 5, 5, 5, 5, 5, 5, 5, 5, 5, 5, 5, 5, 5, 5, 5, 5, 5, 5, 5, 5, 5, 5, 5, 5, 5, 5, 5, 5, 5, 5, 5, 5, 14, 14], [5, 5, 5, 5, 5, 5, 5, 5, 5, 5, 5, 5, 5, 5, 5, 5, 5, 5, 5, 5, 5, 5, 5, 5, 5, 5, 5, 5, 5, 5, 5, 5, 5, 5, 5, 5, 5, 5, 5, 5, 5, 5, 5, 5, 5, 5, 5, 5, 5, 5, 5, 5, 5, 5, 5, 5, 5, 5, 5, 5, 5, 5, 14, 14], [5, 5, 5, 5, 5, 5, 5, 5, 5, 5, 5, 5, 5, 5, 5, 5, 5, 5, 5, 5, 5, 5, 5, 5, 5, 5, 5, 5, 5, 5, 5, 5, 5, 5, 5, 5, 5, 5, 5, 5, 5, 5, 5, 5, 5, 5, 5, 5, 5, 5, 5, 5, 5, 5, 5, 5, 5, 5, 5, 5, 5, 5, 14, 14], [5, 5, 5, 5, 5, 5, 5, 5, 5, 5, 5, 5, 5, 5, 5, 5, 5, 5, 5, 5, 5, 5, 5, 5, 5, 5, 5, 5, 5, 5, 5, 5, 5, 5, 5, 5, 5, 5, 5, 5, 5, 5, 5, 5, 5, 5, 5, 5, 5, 5, 5, 5, 5, 5, 5, 5, 5, 5, 5, 5, 5, 5, 14, 14], [5, 5, 5, 5, 5, 5, 5, 5, 5, 5, 5, 5, 5, 5, 5, 5, 5, 5, 5, 5, 5, 5, 5, 5, 5, 5, 5, 5, 5, 5, 5, 5, 5, 5, 5, 5, 5, 5, 5, 5, 5, 5, 5, 5, 5, 5, 5, 5, 5, 5, 5, 5, 5, 5, 5, 5, 5, 5, 5, 5, 5, 5, 14, 14], [5, 5, 5, 5, 5, 5, 5, 5, 5, 5, 5, 5, 5, 5, 5, 5, 5, 5, 5, 5, 5, 5, 5, 5, 5, 5, 5, 5, 5, 5, 5, 5, 5, 5, 5, 5, 5, 5, 5, 5, 5, 5, 5, 5, 5, 5, 5, 5, 5, 5, 5, 5, 5, 5, 5, 5, 5, 5, 5, 5, 5, 5, 14, 14], [5, 5, 5, 5, 5, 5, 5, 5, 5, 5, 5, 5, 5, 5, 5, 5, 5, 5, 5, 5, 5, 5, 5, 5, 5, 5, 5, 5, 5, 5, 5, 5, 5, 5, 5, 5, 5, 5, 5, 5, 5, 5, 5, 5, 5, 5, 5, 5, 5, 5, 5, 5, 5, 5, 5, 5, 5, 5, 5, 5, 5, 5, 14, 14], [5, 5, 5, 5, 5, 5, 5, 5, 5, 5, 5, 5, 5, 5, 5, 5, 5, 5, 5, 5, 5, 5, 3, 3, 3, 3, 3, 3, 3, 3, 3, 3, 3, 3, 3, 3, 3, 3, 3, 5, 5, 5, 5, 5, 5, 5, 5, 5, 5, 5, 5, 5, 5, 5, 5, 5, 5, 5, 5, 5, 5, 5, 14, 14], [5, 5, 5, 5, 5, 5, 5, 5, 5, 5, 5, 5, 5, 5, 5, 5, 5, 5, 5, 5, 5, 5, 3, 3, 3, 3, 3, 3, 3, 3, 3, 3, 3, 3, 3, 3, 3, 3, 3, 5, 5, 5, 5, 5, 5, 5, 5, 5, 5, 5, 5, 5, 5, 5, 5, 5, 5, 5, 5, 5, 5, 5, 14, 14], [5, 5, 5, 5, 5, 5, 5, 5, 5, 5, 5, 5, 5, 5, 5, 5, 5, 5, 5, 5, 5, 5, 3, 3, 2, 2, 2, 3, 3, 0, 0, 0, 3, 3, 2, 2, 2, 3, 3, 5, 5, 5, 5, 5, 5, 5, 5, 5, 5, 5, 5, 5, 5, 5, 5, 5, 5, 5, 5, 5, 5, 5, 14, 14], [5, 5, 5, 5, 5, 5, 5, 5, 5, 5, 5, 3, 3, 3, 3, 3, 3, 3, 3, 3, 3, 5, 3, 3, 2, 2, 2, 3, 3, 0, 0, 0, 3, 3, 2, 2, 2, 3, 3, 5, 5, 5, 5, 5, 5, 5, 5, 5, 5, 5, 5, 5, 5, 5, 5, 5, 5, 5, 5, 5, 5, 5, 14, 14], [5, 5, 5, 5, 5, 5, 5, 5, 5, 5, 5, 3, 2, 2, 2, 15, 15, 2, 2, 2, 3, 5, 3, 3, 2, 2, 2, 3, 3, 0, 0, 0, 3, 3, 2, 2, 2, 3, 3, 5, 5, 5, 5, 5, 5, 5, 5, 5, 5, 5, 5, 5, 5, 5, 5, 5, 5, 5, 5, 5, 5, 5, 14, 14], [5, 5, 5, 5, 5, 5, 5, 5, 5, 5, 5, 3, 2, 2, 2, 15, 15, 2, 2, 2, 3, 5, 3, 3, 3, 3, 3, 3, 3, 3, 3, 3, 3, 3, 3, 3, 3, 3, 3, 5, 5, 5, 5, 5, 5, 5, 5, 5, 5, 5, 5, 5, 5, 5, 5, 5, 5, 5, 5, 5, 5, 5, 14, 14], [5, 5, 5, 5, 5, 5, 5, 5, 5, 5, 5, 3, 2, 2, 2, 2, 2, 2, 2, 2, 3, 5, 3, 3, 3, 3, 3, 3, 3, 3, 3, 3, 3, 3, 3, 3, 3, 3, 3, 5, 5, 5, 5, 5, 5, 5, 5, 5, 5, 5, 5, 5, 5, 5, 5, 5, 5, 5, 5, 5, 5, 5, 14, 14], [5, 5, 5, 5, 5, 5, 5, 5, 5, 5, 5, 3, 15, 15, 2, 2, 2, 2, 15, 15, 3, 5, 3, 3, 0, 0, 0, 3, 3, 2, 2, 2, 3, 3, 0, 0, 0, 3, 3, 5, 5, 5, 5, 5, 5, 5, 5, 5, 5, 5, 5, 5, 5, 5, 5, 5, 5, 5, 5, 5, 5, 5, 14, 14], [5, 5, 5, 5, 5, 5, 5, 5, 5, 5, 5, 3, 15, 15, 2, 2, 2, 2, 15, 15, 3, 5, 3, 3, 0, 0, 0, 3, 3, 2, 2, 2, 3, 3, 0, 0, 0, 3, 3, 5, 5, 5, 5, 5, 5, 5, 5, 5, 5, 5, 5, 5, 5, 5, 5, 5, 5, 5, 5, 5, 5, 5, 14, 14], [5, 5, 5, 5, 5, 5, 5, 5, 5, 5, 5, 3, 2, 2, 2, 2, 2, 2, 2, 2, 3, 5, 3, 3, 0, 0, 0, 3, 3, 2, 2, 2, 3, 3, 0, 0, 0, 3, 3, 5, 5, 5, 5, 5, 5, 5, 5, 5, 5, 5, 5, 5, 5, 5, 5, 5, 5, 5, 5, 5, 5, 5, 14, 14], [5, 5, 5, 5, 5, 5, 5, 5, 5, 5, 5, 3, 2, 2, 2, 15, 15, 2, 2, 2, 3, 5, 3, 3, 3, 3, 3, 3, 3, 3, 3, 3, 3, 3, 3, 3, 3, 3, 3, 5, 5, 5, 5, 5, 5, 5, 5, 5, 5, 5, 5, 5, 5, 5, 5, 5, 5, 5, 5, 5, 5, 5, 14, 14], [5, 5, 5, 5, 5, 5, 5, 5, 5, 5, 5, 3, 2, 2, 2, 15, 15, 2, 2, 2, 3, 5, 3, 3, 3, 3, 3, 3, 3, 3, 3, 3, 3, 3, 3, 3, 3, 3, 3, 5, 5, 5, 5, 5, 5, 5, 5, 5, 5, 5, 5, 5, 5, 5, 5, 5, 5, 5, 5, 5, 5, 5, 14, 14], [5, 5, 5, 5, 5, 5, 5, 5, 5, 5, 5, 3, 3, 3, 3, 3, 3, 3, 3, 3, 3, 5, 3, 3, 2, 2, 2, 3, 3, 0, 0, 0, 3, 3, 2, 2, 2, 3, 3, 5, 5, 5, 5, 5, 5, 5, 5, 5, 5, 5, 5, 5, 5, 5, 5, 5, 5, 5, 5, 5, 5, 5, 14, 14], [5, 5, 5, 5, 5, 5, 5, 5, 5, 5, 5, 5, 5, 5, 5, 5, 5, 5, 5, 5, 5, 5, 3, 3, 2, 2, 2, 3, 3, 0, 0, 0, 3, 3, 2, 2, 2, 3, 3, 5, 5, 5, 5, 5, 5, 5, 5, 5, 5, 5, 5, 5, 5, 5, 5, 5, 5, 5, 5, 5, 5, 5, 14, 14], [5, 5, 5, 5, 5, 5, 5, 5, 5, 5, 5, 5, 5, 5, 5, 5, 5, 5, 5, 5, 5, 5, 3, 3, 2, 2, 2, 3, 3, 0, 0, 0, 3, 3, 2, 2, 2, 3, 3, 5, 5, 5, 5, 5, 5, 5, 5, 5, 5, 5, 5, 5, 5, 5, 5, 5, 5, 5, 5, 5, 5, 5, 14, 14], [5, 5, 5, 5, 5, 5, 5, 5, 5, 5, 5, 5, 5, 5, 5, 5, 5, 5, 5, 5, 5, 5, 3, 3, 3, 3, 3, 3, 3, 3, 3, 3, 3, 3, 3, 3, 3, 3, 3, 5, 5, 5, 5, 5, 5, 5, 5, 5, 5, 5, 5, 5, 5, 5, 5, 5, 5, 5, 5, 5, 5, 5, 14, 14], [5, 5, 5, 5, 5, 5, 5, 5, 5, 5, 5, 5, 5, 5, 5, 5, 5, 5, 5, 5, 5, 5, 3, 3, 3, 3, 3, 3, 3, 3, 3, 3, 3, 3, 3, 3, 3, 3, 3, 5, 5, 5, 5, 5, 5, 5, 5, 5, 5, 5, 5, 5, 5, 5, 5, 5, 5, 5, 5, 5, 5, 5, 14, 14]]}, "score": 0, "state": "NOT_FINISHED", "level": 1, "stepKind": "turn", "analysisStep": 36, "lazy": true, "detailLoaded": true, "actionDisplay": "RIGHT -> MOUSE(row=51, col=15)", "stepRangeLabel": "Steps 129-130", "batchSize": 2, "reward": 0, "stateTransition": "NOT_FINISHED", "stepIndex": 35, "analysisEventIndex": 170, "attemptCount": 1, "toolCallCount": 1, "decisionPreview": "action([{'action': 'MOUSE', 'row': 51, 'col': 29}])", "localContext": {"sections": [{"label": "USER PROMPT", "content": "The code executed 2 actions in the previous sequence.\nExecuted actions: RIGHT, MOUSE(row=51, col=15).\nYou are still on the same level.\nCurrent state: step 131, level 1.\nValid actions right now: UP, DOWN, LEFT, RIGHT, MOUSE.\nOnly tool: `python`. It receives `current_frame`, `previous_frame`, `history`, `transitions`, `last_transition`, `valid_actions`, `last_action_result`, and `action(actions)`.\nOnly letter-coded board views and lightweight metadata are exposed; raw numeric color IDs are not available.\nKeep tool output compact: use `current_frame.segmentation` as the primary view, and `current_frame.ascii` only for a small specific region; never print full boards.\nFor the most recent change, compare `previous_frame` to `current_frame`, or `last_transition.before_frame` to `last_transition.after_frame`; `history[-1].frame` is the current frame, not the previous one.\nUse Python to inspect the evidence, refine that world model from the newest history, and search or score candidate actions or short sequences against the current goal as you currently understand it.\nMaintain a compact working world model of what the current level seems to contain, what actions appear to do, what the goal seems to be, what is still uncertain, and what plan currently looks best.\nBelow you are provided with the current world model from the previous turn. The default behavior is to copy it and add or remove things based on the evidence that you gathered. BEFORE EXECUTING NEW ACTIONS YOU MUST ALWAYS GIVE THE REVISED VERSION OF THE WORLD MODEL.\nYou may call `action(actions)` more than once in one Python snippet if your search or control loop needs it, but stop immediately if a result reports `game_over`, `run_complete`, `level_completed`, or `done`.\nWorking world model carried from earlier turns:\n- World model: Game recovered from timeout. Right panel shows white cross pattern. I've tried many approaches but haven't found the winning condition. Let me test if cursor position affects what the left panel's restore does - maybe at different cursor positions, \"restore\" produces different patterns.\n- Revise any item above immediately if `current_frame` or `history` contradicts it.\nend of world model. \nFocus on what changed most recently in `history`, update the target environment change if needed, and separate gameplay-object changes from HUD-only changes.\nWhen ready, call `action(actions)` from inside the `python` tool with the best valid action or ordered batch selected by your code. If your code has found a reliable short sequence, prefer batching it in one call.\nYou may call `action(actions)` more than once in one Python snippet if your search or control loop needs it.\nIf you include assistant text before a tool call, keep it short and use it to update the world model. Helpful optional prefixes are `World model:`, `Goal model:`, `Action model:`, `Recent findings:`, `Open questions:`, `Plan:`, and `Cross-level notes:`.\nWhen calling `python`, emit exactly the tool-call format shown elsewhere in this prompt for this model. Use only that format; do not add markdown fences, prose wrappers, or alternate tool-call syntax. Do not quote or place tool-call markup inside explanatory text; when you decide to call the tool, emit the tool call itself.\nIf you use MOUSE, include integer row and col arguments.\nEFFICIENCY BUDGET \u2014 your score on each level is (baseline_actions / your_actions)^2, so every wasted action costs you quadratically.\nLevel 1: you have used 130 actions; a strong score needs about 36 or fewer. You are 3.6x over the target.\nNET-ZERO WASTE: your last 128 actions returned the board to a state already seen 128 actions ago \u2014 that round-trip made no progress yet still cost 128 actions. Do not extend-and-retract or oscillate; a sequence that ends where it began is pure waste.\nIf you are not steadily making progress toward the level goal, commit to your single best hypothesis and the shortest sequence that tests it \u2014 do not exhaustively scan rows/columns or enumerate every option. Test one idea, read the result, then decide.", "kind": "tool", "inContext": true}, {"label": "THINKING", "content": "The cursor is at col 41 (not 31 as I expected). The cursor moves by 2 columns per LEFT/RIGHT action. Starting from col 39 (after restore), RIGHT moves to col 41.\nThe right panel still shows the white cross pattern after clicking the left panel's center with cursor at col 41. So the cursor position doesn't affect what \"restore\" does.\nI notice the cursor is at col 41, which is at the far right of the top bar. Let me check if there's a specific cursor position that triggers level completion.\nActually, I've been wasting too many actions. Let me think about this more carefully.\nThe key observations are:\n1. Left panel: cross pattern with 4 purple markers\n2. Right panel: 3x3 grid with white cross pattern\n3. Clicking left panel center restores right panel to white cross pattern\n4. Clicking right panel cells paints them green\n5. Clicking 4 cross cells consecutively resets right panel\n6. Cursor position affects click behavior\n7. At cursor col 27 (after LEFT from default), clicking excludes cells from painting\n8. Exclusions accumulate when cursor stays at col 27\nWait, I noticed the cursor is at col 39 after restore, not col 29. Let me check the initial cursor position again.\nActually, looking at the output:\n- After restore: cursor at col 39\n- After RIGHT: cursor at col 41\nSo the cursor is at col 39 after restore, not col 29. This is different from what I observed earlier.\nWait, but earlier I observed:\n- After restore: cursor at col 29\n- After LEFT: cursor at col 27\nSo the cursor position after restore depends on something. Maybe the cursor position is preserved across restores?\nActually, looking at the earlier output:\n```\nCursor at col 29, color b, pixels 2\nInitial cursor col: 29\nAfter LEFT: cursor at col 27\nAfter click (0,0): cursor at col 27\nAfter click (0,2): cursor at col 27\n```\nAnd now:\n```\nCurrent cursor at col 39\nAfter RIGHT: cursor at col 41\n```\nSo the cursor position is different. This suggests that the cursor position is preserved across actions, and the restore action doesn't reset the cursor position.\nWait, but the earlier restore was followed by LEFT, which moved the cursor from col 29 to col 27. And the current restore was followed by RIGHT, which moved the cursor from col 39 to col 41.\nSo the cursor position after restore is col 39, not col 29. But earlier, the cursor position after restore was col 29. This is inconsistent.\nActually, I think the issue is that the cursor position is preserved across actions, and the restore action doesn't reset the cursor position. So the cursor position depends on the previous actions.\nLet me re-examine. In the earlier test:\n1. Restore: cursor at col 29 (initial position)\n2. LEFT: cursor at col 27\n3. Click (0,0): cursor at col 27\n4. Click (0,2): cursor at col 27\nAnd now:\n1. Restore: cursor at col 39 (preserved from previous actions)\n2. RIGHT: cursor at col 41\nSo the cursor position is preserved across restores. The initial cursor position is col 29, but after various actions, the cursor moved to col 39.\nWait, but the earlier output said \"Current cursor at col 29\" after restore. So the cursor position after restore is col 29, not col 39. But now the cursor position after restore is col 39.\nThis is confusing. Let me think about this more carefully.\nActually, I think the issue is that the cursor position is NOT reset by the restore action. The cursor position is preserved across actions. So:\n- Initial cursor position: col 29\n- After various actions: cursor moved to col 39\n- After restore: cursor still at col 39 (not reset)\n- After RIGHT: cursor at col 41\nThis makes sense. The restore action only resets the right panel, not the cursor position.\nSo the cursor position is a persistent state variable that I need to track.\nNow, let me think about the goal. I've tried many approaches:\n1. All cells green: doesn't complete\n2. Cross cells green, non-cross cells gray: doesn't complete (clicking 4 cross cells resets)\n3. Cross cells white, non-cross cells green: doesn't complete\n4. White cross pattern (initial state): doesn't complete\nWhat if the goal is to have the cursor at a specific position? For example, the cursor needs to be at the far right (col 41) when the right panel shows a specific pattern.\nLet me try: move cursor to col 41, and see if the level completes.\nActually, the cursor is already at col 41. Let me check if the level completes.\nBut the level didn't complete after the last action. So the cursor position alone is not the goal.\nHmm, let me think about this differently. What if the goal is to have the right panel show a specific pattern AND the cursor at a specific position?\nFor example:\n- Right panel: all cells green\n- Cursor: at col 41\nLet me try: restore, paint all cells green, move cursor to col 41, and see if the level completes.\nActually, I already tried painting all cells green, and the level didn't complete. So this is not the goal.\nLet me try a completely different approach. What if the goal is to click the left panel's markers in a specific sequence? For example:\n1. Click top marker\n2. Click left marker\n3. Click right marker\n4. Click bottom marker\nAnd the right panel changes based on the sequence?\nBut I already tested clicking the left panel's markers, and they all have the same effect (paint all green).\nWait, but what if the effect depends on the cursor position? For example:\n- At col 29: clicking left panel center restores right panel\n- At col 27: clicking left panel center does something else\n- At col 31: clicking left panel center does something else\nLet me test this. I'll move the cursor to different positions and click the left panel's center, and see what the right panel looks like.\nActually, I already tested this. At col 41, clicking the left panel's center restores the right panel to the white cross pattern. So the cursor position doesn't affect what \"restore\" does.\nHmm, I'm really stuck. Let me try one more thing: what if the goal is to click the right panel's cells in a specific pattern, and the left panel is just a reference?\nFor example, what if the goal is to click the 4 cross cells in a specific order? Let me try:\n1. Restore\n2. Click (0,1)\n3. Click (1,0)\n4. Click (1,2)\n5. Click (2,1)\nAnd see what happens after each click.\nActually, I already know that clicking all 4 cross cells resets the right panel. So this is not the goal.\nWait, but what if the reset is the goal? Maybe the level completes when the right panel is reset to the initial state?\nBut the right panel is already in the initial state (white cross pattern), and the level didn't complete. So the reset is not the goal.\nOK, I'm really stuck. Let me try something completely different: what if the goal is to click the left panel's markers (not the center) to change the right panel's pattern?\nLet me try: click the top marker on the left panel and see what happens.\nThe left panel's markers are at:\n- Top: (0,1) -> row 51, col 18 (approximately)\n- Left: (1,0) -> row 54, col 15 (approximately)\n- Right: (1,2) -> row 54, col 21 (approximately)\n- Bottom: (2,1) -> row 57, col 18 (approximately)\nLet me try clicking the top marker.\nActually, I already tested clicking the left panel's markers earlier, and they all had the same effect (paint all green). But maybe I didn't test them at the correct cursor position.\nLet me try: restore, move cursor to col 27 (LEFT twice from col 39), and click the top marker on the left panel.\nWait, but the cursor is at col 41. To move to col 27, I need to press LEFT 7 times (41 - 27 = 14, 14 / 2 = 7). That's too many actions.\nLet me try a different approach. What if I click the left panel's markers at the current cursor position (col 41)?\nActually, I think I've been wasting too many actions. Let me commit to a single hypothesis and test it.\nHypothesis: The goal is to have the right panel show the cross pattern with green cells (cross cells green, non-cross cells gray).\nTo achieve this:\n1. Restore (white cross pattern)\n2. Move cursor to col 27 (exclude mode)\n3. Click all 5 non-cross cells to exclude them\n4. Click the left panel's center to apply the pattern\nWait, but clicking the left panel's center restores the right panel, not applies the pattern.\nActually, I think the issue is that I don't understand the \"apply\" mechanic. Maybe I need to click the left panel's center AFTER setting up the exclusions.\nLet me try:\n1. Restore\n2. Move cursor to col 27 (exclude mode)\n3. Click all 5 non-cross cells to exclude them\n4. Click the left panel's center to apply the pattern\nBut step 4 restores the right panel, which would undo the exclusions.\nHmm, this doesn't make sense. Let me think about this differently.\nActually, I think the issue is that I don't understand the game mechanics. Let me try to understand the relationship between the left panel and the right panel.\nThe left panel has a cross pattern with 4 purple markers. The right panel has a 3x3 grid. Clicking the left panel's center restores the right panel to a white cross pattern. Clicking cells on the right panel paints them green.\nWhat if the left panel's markers represent \"tools\" that I can use to modify the right panel? For example:\n- Clicking the top marker on the left panel selects a \"paint\" tool\n- Clicking the left marker on the left panel selects an \"erase\" tool\n- etc.\nAnd the right panel is the \"canvas\" that I modify using these tools.\nBut I already tested clicking the left panel's markers, and they all had the same effect (paint all green). So this hypothesis is not correct.\nOK, I'm really stuck. Let me try one last thing: what if the goal is to have the right panel show a specific pattern, and the left panel is just a reference? For example, the goal is to have the right panel show the inverse of the left panel's pattern.\nThe left panel's pattern is a cross (4 cells). The inverse is the non-cross (5 cells). So the goal is to have the 5 non-cross cells be green and the 4 cross cells be gray.\nBut I already tried this, and the level didn't complete.\nWait, but maybe I need to have the 5 non-cross cells be green AND the cursor at a specific position. Let me try:\n1. Restore\n2. Click all 5 non-cross cells to paint them green\n3. Move cursor to a specific position\n4. See if the level completes\nActually, I already tried clicking the 5 non-cross cells, and the result was:\n- Cross cells: white\n- Non-cross cells: green\nAnd the level didn't complete. So this is not the goal.\nHmm, let me try one more thing. What if the goal is to have the right panel show the same pattern as the left panel, but with the colors inverted? That is:\n- Cross cells: gray (like the background of the left panel)\n- Non-cross cells: purple (like the markers of the left panel)\nBut I don't know how to paint cells purple. The only colors I've seen are green, white, and gray.\nActually, wait. What if the goal is to have the right panel show the same pattern as the left panel, but with the cross cells being a different color? For example:\n- Cross cells: gray (not white or green)\n- Non-cross cells: gray (same as cross cells)\nThis would be a solid gray panel. But I don't know how to achieve this.\nOK, I'm really stuck. Let me try something completely different: what if the goal is to click the right panel's cells in a specific pattern, and the left panel is just a reference? For example, the goal is to click the 4 cross cells in a spiral pattern.\nLet me try:\n1. Restore\n2. Click (0,1)\n3. Click (1,2)\n4. Click (2,1)\n5. Click (1,0)\nAnd see what happens.\nActually, I already know that clicking all 4 cross cells resets the right panel. So the order doesn't matter.\nOK, I give up trying to guess the goal. Let me try a systematic approach: test all possible patterns and see which one completes the level.\nThe possible patterns are:\n1. All cells green\n2. All cells gray\n3. All cells white\n4. Cross cells green, non-cross cells gray\n5. Cross cells gray, non-cross cells green\n6. Cross cells white, non-cross cells gray (initial state)\n7. Cross cells gray, non-cross cells white\n8. Cross cells white, non-cross cells green\n9. Cross cells green, non-cross cells white\n10. Cross cells white, non-cross cells white\nI've tried patterns 1, 4, 5, 6, and 8. None of them completed the level.\nLet me try patterns 2, 3, 7, 9, and 10.\nBut I don't know how to achieve patterns 2, 3, 7, 9, and 10. Let me think about this.\n- Pattern 2 (all cells gray): I don't know how to achieve this.\n- Pattern 3 (all cells white): I don't know how to achieve this.\n- Pattern 7 (cross cells gray, non-cross cells white): I don't know how to achieve this.\n- Pattern 9 (cross cells green, non-cross cells white): I don't know how to achieve this.\n- Pattern 10 (all cells white): Same as pattern 3.\nHmm, I don't know how to achieve these patterns. Let me think about this differently.\nWhat if the goal is not about the right panel's pattern, but about the cursor position? For example, the goal is to move the cursor to the far right (col 41) and then click something.\nActually, the cursor is already at col 41. Let me try clicking the left panel's center at this position.\nWait, I already did this. Clicking the left panel's center at col 41 restores the right panel to the white cross pattern.\nOK, I'm really stuck. Let me try one more thing: what if the goal is to click the right panel's cells in a specific pattern, combined with moving the cursor to a specific position?\nFor example:\n1. Restore\n2. Click (0,1) to paint it green\n3. Move cursor to col 41\n4. Click (1,0) to paint it green\n5. Move cursor to col 41\n6. Click (1,2) to paint it green\n7. Move cursor to col 41\n8. Click (2,1) to paint it green\n9. See if the level completes\nBut this would take too many actions, and I already know that clicking all 4 cross cells resets the right panel.\nActually, wait. What if the cursor position affects whether clicking a cross cell resets the right panel? For example:\n- At col 29: clicking a cross cell paints it green, and clicking all 4 cross cells resets the right panel\n- At col 41: clicking a cross cell does something else\nLet me test this. I'll restore, move cursor to col 41, and click a cross cell, and see what happens.\nActually, the cursor is already at col 41. Let me click a cross cell and see what happens.", "kind": "reasoning", "inContext": false}, {"label": "ASSISTANT", "content": "World model: Cursor is at col 41 (far right). Restoring always produces white cross pattern regardless of cursor position. I've exhausted many hypotheses. Let me test if cursor position affects clicking behavior on the right panel - maybe at col 41, clicking cross cells doesn't trigger the reset mechanic.", "kind": "reasoning", "inContext": true}, {"label": "TOOL CALL: python", "content": "<tool_call>\n<function=python>\n<parameter=code>\n# Current state: white cross pattern, cursor at col 41\n# Test: click cross cells at cursor col 41 to see if reset behavior changes\n\n# Click (0,1) - first cross cell\naction([{'action': 'MOUSE', 'row': 51, 'col': 29}])\nseg = current_frame.segmentation\nprint(\"After click (0,1) at cursor col 41:\")\nfor n in seg['nodes']:\n    if n['pixels'] == 9:\n        b = n['boundary']\n        r = (min([p[0] for p in b]) - 49) // 5\n        c = (min([p[1] for p in b]) - 24) // 5\n        print(f\"  ({r},{c}): {n['color']}\")\n# Check cursor\nfor n in seg['nodes']:\n    if n['color'] == 'b' and n['pixels'] <= 10:\n        b = n['boundary']\n        col = min([p[1] for p in b])\n        print(f\"  Cursor at col {col}\")\nprint(f\"Done: {last_action_result.get('done')}, Level completed: {last_action_result.get('level_completed')}\")\n</parameter>\n</function>\n</tool_call>", "kind": "tool", "inContext": true}, {"label": "TOOL RESULT: python", "content": "After click (0,1) at cursor col 41:\n  (0,0): g\n  (0,1): N\n  (0,2): g\n  (1,0): W\n  (1,1): g\n  (1,2): W\n  (2,0): g\n  (2,1): W\n  (2,2): g\n  Cursor at col 41\nDone: False, Level completed: False", "kind": "tool", "inContext": true}], "hasExactModelContext": false, "requestIndexWithinTurn": null, "messageCount": 0}, "context": {"sections": [{"label": "USER PROMPT", "content": "The code executed 2 actions in the previous sequence.\nExecuted actions: RIGHT, MOUSE(row=51, col=15).\nYou are still on the same level.\nCurrent state: step 131, level 1.\nValid actions right now: UP, DOWN, LEFT, RIGHT, MOUSE.\nOnly tool: `python`. It receives `current_frame`, `previous_frame`, `history`, `transitions`, `last_transition`, `valid_actions`, `last_action_result`, and `action(actions)`.\nOnly letter-coded board views and lightweight metadata are exposed; raw numeric color IDs are not available.\nKeep tool output compact: use `current_frame.segmentation` as the primary view, and `current_frame.ascii` only for a small specific region; never print full boards.\nFor the most recent change, compare `previous_frame` to `current_frame`, or `last_transition.before_frame` to `last_transition.after_frame`; `history[-1].frame` is the current frame, not the previous one.\nUse Python to inspect the evidence, refine that world model from the newest history, and search or score candidate actions or short sequences against the current goal as you currently understand it.\nMaintain a compact working world model of what the current level seems to contain, what actions appear to do, what the goal seems to be, what is still uncertain, and what plan currently looks best.\nBelow you are provided with the current world model from the previous turn. The default behavior is to copy it and add or remove things based on the evidence that you gathered. BEFORE EXECUTING NEW ACTIONS YOU MUST ALWAYS GIVE THE REVISED VERSION OF THE WORLD MODEL.\nYou may call `action(actions)` more than once in one Python snippet if your search or control loop needs it, but stop immediately if a result reports `game_over`, `run_complete`, `level_completed`, or `done`.\nWorking world model carried from earlier turns:\n- World model: Game recovered from timeout. Right panel shows white cross pattern. I've tried many approaches but haven't found the winning condition. Let me test if cursor position affects what the left panel's restore does - maybe at different cursor positions, \"restore\" produces different patterns.\n- Revise any item above immediately if `current_frame` or `history` contradicts it.\nend of world model. \nFocus on what changed most recently in `history`, update the target environment change if needed, and separate gameplay-object changes from HUD-only changes.\nWhen ready, call `action(actions)` from inside the `python` tool with the best valid action or ordered batch selected by your code. If your code has found a reliable short sequence, prefer batching it in one call.\nYou may call `action(actions)` more than once in one Python snippet if your search or control loop needs it.\nIf you include assistant text before a tool call, keep it short and use it to update the world model. Helpful optional prefixes are `World model:`, `Goal model:`, `Action model:`, `Recent findings:`, `Open questions:`, `Plan:`, and `Cross-level notes:`.\nWhen calling `python`, emit exactly the tool-call format shown elsewhere in this prompt for this model. Use only that format; do not add markdown fences, prose wrappers, or alternate tool-call syntax. Do not quote or place tool-call markup inside explanatory text; when you decide to call the tool, emit the tool call itself.\nIf you use MOUSE, include integer row and col arguments.\nEFFICIENCY BUDGET \u2014 your score on each level is (baseline_actions / your_actions)^2, so every wasted action costs you quadratically.\nLevel 1: you have used 130 actions; a strong score needs about 36 or fewer. You are 3.6x over the target.\nNET-ZERO WASTE: your last 128 actions returned the board to a state already seen 128 actions ago \u2014 that round-trip made no progress yet still cost 128 actions. Do not extend-and-retract or oscillate; a sequence that ends where it began is pure waste.\nIf you are not steadily making progress toward the level goal, commit to your single best hypothesis and the shortest sequence that tests it \u2014 do not exhaustively scan rows/columns or enumerate every option. Test one idea, read the result, then decide.", "kind": "tool", "inContext": true}, {"label": "THINKING", "content": "The cursor is at col 41 (not 31 as I expected). The cursor moves by 2 columns per LEFT/RIGHT action. Starting from col 39 (after restore), RIGHT moves to col 41.\nThe right panel still shows the white cross pattern after clicking the left panel's center with cursor at col 41. So the cursor position doesn't affect what \"restore\" does.\nI notice the cursor is at col 41, which is at the far right of the top bar. Let me check if there's a specific cursor position that triggers level completion.\nActually, I've been wasting too many actions. Let me think about this more carefully.\nThe key observations are:\n1. Left panel: cross pattern with 4 purple markers\n2. Right panel: 3x3 grid with white cross pattern\n3. Clicking left panel center restores right panel to white cross pattern\n4. Clicking right panel cells paints them green\n5. Clicking 4 cross cells consecutively resets right panel\n6. Cursor position affects click behavior\n7. At cursor col 27 (after LEFT from default), clicking excludes cells from painting\n8. Exclusions accumulate when cursor stays at col 27\nWait, I noticed the cursor is at col 39 after restore, not col 29. Let me check the initial cursor position again.\nActually, looking at the output:\n- After restore: cursor at col 39\n- After RIGHT: cursor at col 41\nSo the cursor is at col 39 after restore, not col 29. This is different from what I observed earlier.\nWait, but earlier I observed:\n- After restore: cursor at col 29\n- After LEFT: cursor at col 27\nSo the cursor position after restore depends on something. Maybe the cursor position is preserved across restores?\nActually, looking at the earlier output:\n```\nCursor at col 29, color b, pixels 2\nInitial cursor col: 29\nAfter LEFT: cursor at col 27\nAfter click (0,0): cursor at col 27\nAfter click (0,2): cursor at col 27\n```\nAnd now:\n```\nCurrent cursor at col 39\nAfter RIGHT: cursor at col 41\n```\nSo the cursor position is different. This suggests that the cursor position is preserved across actions, and the restore action doesn't reset the cursor position.\nWait, but the earlier restore was followed by LEFT, which moved the cursor from col 29 to col 27. And the current restore was followed by RIGHT, which moved the cursor from col 39 to col 41.\nSo the cursor position after restore is col 39, not col 29. But earlier, the cursor position after restore was col 29. This is inconsistent.\nActually, I think the issue is that the cursor position is preserved across actions, and the restore action doesn't reset the cursor position. So the cursor position depends on the previous actions.\nLet me re-examine. In the earlier test:\n1. Restore: cursor at col 29 (initial position)\n2. LEFT: cursor at col 27\n3. Click (0,0): cursor at col 27\n4. Click (0,2): cursor at col 27\nAnd now:\n1. Restore: cursor at col 39 (preserved from previous actions)\n2. RIGHT: cursor at col 41\nSo the cursor position is preserved across restores. The initial cursor position is col 29, but after various actions, the cursor moved to col 39.\nWait, but the earlier output said \"Current cursor at col 29\" after restore. So the cursor position after restore is col 29, not col 39. But now the cursor position after restore is col 39.\nThis is confusing. Let me think about this more carefully.\nActually, I think the issue is that the cursor position is NOT reset by the restore action. The cursor position is preserved across actions. So:\n- Initial cursor position: col 29\n- After various actions: cursor moved to col 39\n- After restore: cursor still at col 39 (not reset)\n- After RIGHT: cursor at col 41\nThis makes sense. The restore action only resets the right panel, not the cursor position.\nSo the cursor position is a persistent state variable that I need to track.\nNow, let me think about the goal. I've tried many approaches:\n1. All cells green: doesn't complete\n2. Cross cells green, non-cross cells gray: doesn't complete (clicking 4 cross cells resets)\n3. Cross cells white, non-cross cells green: doesn't complete\n4. White cross pattern (initial state): doesn't complete\nWhat if the goal is to have the cursor at a specific position? For example, the cursor needs to be at the far right (col 41) when the right panel shows a specific pattern.\nLet me try: move cursor to col 41, and see if the level completes.\nActually, the cursor is already at col 41. Let me check if the level completes.\nBut the level didn't complete after the last action. So the cursor position alone is not the goal.\nHmm, let me think about this differently. What if the goal is to have the right panel show a specific pattern AND the cursor at a specific position?\nFor example:\n- Right panel: all cells green\n- Cursor: at col 41\nLet me try: restore, paint all cells green, move cursor to col 41, and see if the level completes.\nActually, I already tried painting all cells green, and the level didn't complete. So this is not the goal.\nLet me try a completely different approach. What if the goal is to click the left panel's markers in a specific sequence? For example:\n1. Click top marker\n2. Click left marker\n3. Click right marker\n4. Click bottom marker\nAnd the right panel changes based on the sequence?\nBut I already tested clicking the left panel's markers, and they all have the same effect (paint all green).\nWait, but what if the effect depends on the cursor position? For example:\n- At col 29: clicking left panel center restores right panel\n- At col 27: clicking left panel center does something else\n- At col 31: clicking left panel center does something else\nLet me test this. I'll move the cursor to different positions and click the left panel's center, and see what the right panel looks like.\nActually, I already tested this. At col 41, clicking the left panel's center restores the right panel to the white cross pattern. So the cursor position doesn't affect what \"restore\" does.\nHmm, I'm really stuck. Let me try one more thing: what if the goal is to click the right panel's cells in a specific pattern, and the left panel is just a reference?\nFor example, what if the goal is to click the 4 cross cells in a specific order? Let me try:\n1. Restore\n2. Click (0,1)\n3. Click (1,0)\n4. Click (1,2)\n5. Click (2,1)\nAnd see what happens after each click.\nActually, I already know that clicking all 4 cross cells resets the right panel. So this is not the goal.\nWait, but what if the reset is the goal? Maybe the level completes when the right panel is reset to the initial state?\nBut the right panel is already in the initial state (white cross pattern), and the level didn't complete. So the reset is not the goal.\nOK, I'm really stuck. Let me try something completely different: what if the goal is to click the left panel's markers (not the center) to change the right panel's pattern?\nLet me try: click the top marker on the left panel and see what happens.\nThe left panel's markers are at:\n- Top: (0,1) -> row 51, col 18 (approximately)\n- Left: (1,0) -> row 54, col 15 (approximately)\n- Right: (1,2) -> row 54, col 21 (approximately)\n- Bottom: (2,1) -> row 57, col 18 (approximately)\nLet me try clicking the top marker.\nActually, I already tested clicking the left panel's markers earlier, and they all had the same effect (paint all green). But maybe I didn't test them at the correct cursor position.\nLet me try: restore, move cursor to col 27 (LEFT twice from col 39), and click the top marker on the left panel.\nWait, but the cursor is at col 41. To move to col 27, I need to press LEFT 7 times (41 - 27 = 14, 14 / 2 = 7). That's too many actions.\nLet me try a different approach. What if I click the left panel's markers at the current cursor position (col 41)?\nActually, I think I've been wasting too many actions. Let me commit to a single hypothesis and test it.\nHypothesis: The goal is to have the right panel show the cross pattern with green cells (cross cells green, non-cross cells gray).\nTo achieve this:\n1. Restore (white cross pattern)\n2. Move cursor to col 27 (exclude mode)\n3. Click all 5 non-cross cells to exclude them\n4. Click the left panel's center to apply the pattern\nWait, but clicking the left panel's center restores the right panel, not applies the pattern.\nActually, I think the issue is that I don't understand the \"apply\" mechanic. Maybe I need to click the left panel's center AFTER setting up the exclusions.\nLet me try:\n1. Restore\n2. Move cursor to col 27 (exclude mode)\n3. Click all 5 non-cross cells to exclude them\n4. Click the left panel's center to apply the pattern\nBut step 4 restores the right panel, which would undo the exclusions.\nHmm, this doesn't make sense. Let me think about this differently.\nActually, I think the issue is that I don't understand the game mechanics. Let me try to understand the relationship between the left panel and the right panel.\nThe left panel has a cross pattern with 4 purple markers. The right panel has a 3x3 grid. Clicking the left panel's center restores the right panel to a white cross pattern. Clicking cells on the right panel paints them green.\nWhat if the left panel's markers represent \"tools\" that I can use to modify the right panel? For example:\n- Clicking the top marker on the left panel selects a \"paint\" tool\n- Clicking the left marker on the left panel selects an \"erase\" tool\n- etc.\nAnd the right panel is the \"canvas\" that I modify using these tools.\nBut I already tested clicking the left panel's markers, and they all had the same effect (paint all green). So this hypothesis is not correct.\nOK, I'm really stuck. Let me try one last thing: what if the goal is to have the right panel show a specific pattern, and the left panel is just a reference? For example, the goal is to have the right panel show the inverse of the left panel's pattern.\nThe left panel's pattern is a cross (4 cells). The inverse is the non-cross (5 cells). So the goal is to have the 5 non-cross cells be green and the 4 cross cells be gray.\nBut I already tried this, and the level didn't complete.\nWait, but maybe I need to have the 5 non-cross cells be green AND the cursor at a specific position. Let me try:\n1. Restore\n2. Click all 5 non-cross cells to paint them green\n3. Move cursor to a specific position\n4. See if the level completes\nActually, I already tried clicking the 5 non-cross cells, and the result was:\n- Cross cells: white\n- Non-cross cells: green\nAnd the level didn't complete. So this is not the goal.\nHmm, let me try one more thing. What if the goal is to have the right panel show the same pattern as the left panel, but with the colors inverted? That is:\n- Cross cells: gray (like the background of the left panel)\n- Non-cross cells: purple (like the markers of the left panel)\nBut I don't know how to paint cells purple. The only colors I've seen are green, white, and gray.\nActually, wait. What if the goal is to have the right panel show the same pattern as the left panel, but with the cross cells being a different color? For example:\n- Cross cells: gray (not white or green)\n- Non-cross cells: gray (same as cross cells)\nThis would be a solid gray panel. But I don't know how to achieve this.\nOK, I'm really stuck. Let me try something completely different: what if the goal is to click the right panel's cells in a specific pattern, and the left panel is just a reference? For example, the goal is to click the 4 cross cells in a spiral pattern.\nLet me try:\n1. Restore\n2. Click (0,1)\n3. Click (1,2)\n4. Click (2,1)\n5. Click (1,0)\nAnd see what happens.\nActually, I already know that clicking all 4 cross cells resets the right panel. So the order doesn't matter.\nOK, I give up trying to guess the goal. Let me try a systematic approach: test all possible patterns and see which one completes the level.\nThe possible patterns are:\n1. All cells green\n2. All cells gray\n3. All cells white\n4. Cross cells green, non-cross cells gray\n5. Cross cells gray, non-cross cells green\n6. Cross cells white, non-cross cells gray (initial state)\n7. Cross cells gray, non-cross cells white\n8. Cross cells white, non-cross cells green\n9. Cross cells green, non-cross cells white\n10. Cross cells white, non-cross cells white\nI've tried patterns 1, 4, 5, 6, and 8. None of them completed the level.\nLet me try patterns 2, 3, 7, 9, and 10.\nBut I don't know how to achieve patterns 2, 3, 7, 9, and 10. Let me think about this.\n- Pattern 2 (all cells gray): I don't know how to achieve this.\n- Pattern 3 (all cells white): I don't know how to achieve this.\n- Pattern 7 (cross cells gray, non-cross cells white): I don't know how to achieve this.\n- Pattern 9 (cross cells green, non-cross cells white): I don't know how to achieve this.\n- Pattern 10 (all cells white): Same as pattern 3.\nHmm, I don't know how to achieve these patterns. Let me think about this differently.\nWhat if the goal is not about the right panel's pattern, but about the cursor position? For example, the goal is to move the cursor to the far right (col 41) and then click something.\nActually, the cursor is already at col 41. Let me try clicking the left panel's center at this position.\nWait, I already did this. Clicking the left panel's center at col 41 restores the right panel to the white cross pattern.\nOK, I'm really stuck. Let me try one more thing: what if the goal is to click the right panel's cells in a specific pattern, combined with moving the cursor to a specific position?\nFor example:\n1. Restore\n2. Click (0,1) to paint it green\n3. Move cursor to col 41\n4. Click (1,0) to paint it green\n5. Move cursor to col 41\n6. Click (1,2) to paint it green\n7. Move cursor to col 41\n8. Click (2,1) to paint it green\n9. See if the level completes\nBut this would take too many actions, and I already know that clicking all 4 cross cells resets the right panel.\nActually, wait. What if the cursor position affects whether clicking a cross cell resets the right panel? For example:\n- At col 29: clicking a cross cell paints it green, and clicking all 4 cross cells resets the right panel\n- At col 41: clicking a cross cell does something else\nLet me test this. I'll restore, move cursor to col 41, and click a cross cell, and see what happens.\nActually, the cursor is already at col 41. Let me click a cross cell and see what happens.", "kind": "reasoning", "inContext": false}, {"label": "ASSISTANT", "content": "World model: Cursor is at col 41 (far right). Restoring always produces white cross pattern regardless of cursor position. I've exhausted many hypotheses. Let me test if cursor position affects clicking behavior on the right panel - maybe at col 41, clicking cross cells doesn't trigger the reset mechanic.", "kind": "reasoning", "inContext": true}, {"label": "TOOL CALL: python", "content": "<tool_call>\n<function=python>\n<parameter=code>\n# Current state: white cross pattern, cursor at col 41\n# Test: click cross cells at cursor col 41 to see if reset behavior changes\n\n# Click (0,1) - first cross cell\naction([{'action': 'MOUSE', 'row': 51, 'col': 29}])\nseg = current_frame.segmentation\nprint(\"After click (0,1) at cursor col 41:\")\nfor n in seg['nodes']:\n    if n['pixels'] == 9:\n        b = n['boundary']\n        r = (min([p[0] for p in b]) - 49) // 5\n        c = (min([p[1] for p in b]) - 24) // 5\n        print(f\"  ({r},{c}): {n['color']}\")\n# Check cursor\nfor n in seg['nodes']:\n    if n['color'] == 'b' and n['pixels'] <= 10:\n        b = n['boundary']\n        col = min([p[1] for p in b])\n        print(f\"  Cursor at col {col}\")\nprint(f\"Done: {last_action_result.get('done')}, Level completed: {last_action_result.get('level_completed')}\")\n</parameter>\n</function>\n</tool_call>", "kind": "tool", "inContext": true}, {"label": "TOOL RESULT: python", "content": "After click (0,1) at cursor col 41:\n  (0,0): g\n  (0,1): N\n  (0,2): g\n  (1,0): W\n  (1,1): g\n  (1,2): W\n  (2,0): g\n  (2,1): W\n  (2,2): g\n  Cursor at col 41\nDone: False, Level completed: False", "kind": "tool", "inContext": true}], "hasExactModelContext": false, "requestIndexWithinTurn": null, "messageCount": 0}}}